redis_pydantic/__init__.py
redis_pydantic/base.py
redis_pydantic/config.py
redis_pydantic/context.py
redis_pydantic/errors/__init__.py
redis_pydantic/errors/base.py
redis_pydantic/py.typed
redis_pydantic/types/__init__.py
redis_pydantic/types/any.py
redis_pydantic/types/base.py
redis_pydantic/types/boolean.py
redis_pydantic/types/byte.py
redis_pydantic/types/datetime.py
redis_pydantic/types/dct.py
redis_pydantic/types/init.py
redis_pydantic/types/integer.py
redis_pydantic/types/lst.py
redis_pydantic/types/string.py
redis_pydantic/types/utils.py
redis_pydantic/utils.py
redis_pydantic-1.2.2.dist-info/METADATA
redis_pydantic-1.2.2.dist-info/WHEEL
redis_pydantic-1.2.2.dist-info/RECORD
