Metadata-Version: 2.4
Name: redis-pydantic
Version: 1.2.2
Summary: Pydantic models with Redis as the backend
License: MIT
Keywords: redis,pydantic,orm,database,async
Author: YedidyaHKfir
Author-email: your.email@example.com
Requires-Python: >=3.10,<4.0
Classifier: Development Status :: 3 - Alpha
Classifier: Intended Audience :: Developers
Classifier: License :: OSI Approved :: MIT License
Classifier: Programming Language :: Python :: 3
Classifier: Programming Language :: Python :: 3.10
Classifier: Programming Language :: Python :: 3.11
Classifier: Programming Language :: Python :: 3.12
Classifier: Programming Language :: Python :: 3.13
Classifier: Programming Language :: Python :: 3.14
Classifier: Topic :: Database
Classifier: Topic :: Software Development :: Libraries :: Python Modules
Requires-Dist: pydantic (>=2.11.9)
Requires-Dist: redis[async] (>=6.4.0)
Project-URL: Documentation, https://github.com/YedidyaHKfir/redis-pydantic
Project-URL: Homepage, https://github.com/YedidyaHKfir/redis-pydantic
Project-URL: Repository, https://github.com/YedidyaHKfir/redis-pydantic
